{
    "coctails": [
        {
            "id": 1,
            "name": "Bloody Mary",
            "color": "Red",
            "ingredient": "Tomato",
            "alcohol": true
        },
        {
            "id": 1,
            "name": "Cosmopolitan",
            "color": "Pink",
            "ingredient": "Blueberry",
            "alcohol": true
        },
        {
            "id": 1,
            "name": "Piña Colada",
            "color": "White",
            "ingredient": "Pineapple",
            "alcohol": false
        }
    ]
}
